{
  "schema_version": "1",
  "data_file": "/Users/mine/git/zdsim/zdsim/data/zerodose_data_formated.xlsx",
  "calibration_source": "loaded: /Users/mine/git/zdsim/calibration.json",
  "projection_calendar_start": 2025,
  "projection_calendar_stop": 2030,
  "years": 5,
  "n_agents": 20000,
  "calibration_short_run_years": 8,
  "calibration_short_run_agents": 10000,
  "empirical_zerodose_proxy_dtp1": {
    "mean_zerodose_proxy": 0.1647298685507964,
    "std_zerodose_proxy": 0.06431024802344402,
    "mean_dtp1_coverage_proxy": 0.8352701314492037,
    "n_months": 84,
    "years_span": "2018-2024"
  },
  "empirical_disease_context_monthly": {
    "pneumonia": {
      "mean_monthly_cases": 756409.4858630953,
      "min_monthly_cases": 346374.0,
      "max_monthly_cases": 1325802.0,
      "n_months": 84
    },
    "measles": {
      "mean_monthly_cases": 2907.3333333333335,
      "min_monthly_cases": 944.0,
      "max_monthly_cases": 10272.0,
      "n_months": 84
    },
    "tetanus": {
      "mean_monthly_cases": 594.7619047619048,
      "min_monthly_cases": 196.0,
      "max_monthly_cases": 2082.0,
      "n_months": 84
    }
  },
  "zero_dose_fraction_under5_empirical_proxy": 0.1647298685507964,
  "zero_dose_fraction_under5_model_counterfactual_no_intervention": 1.0,
  "zero_dose_fraction_under5_model_baseline": 0.14829322887520985,
  "zero_dose_fraction_under5_model_scale_up": 0.07218212104386452,
  "relative_reduction_percent_model": 51.32473573381664,
  "model_reference_routine_prob": 0.029076923076923077,
  "model_scale_up_routine_prob": 0.06687692307692307,
  "model_scale_up_coverage": 0.8552701314492037,
  "calibration_reference_parameters": {
    "seed": 42,
    "birth_rate": 25.0,
    "death_rate": 8.0,
    "household_contacts": 5,
    "community_contacts": 15,
    "tetanus_init_p": 0.001,
    "intervention_routine_prob": 0.029076923076923077,
    "intervention_coverage": 0.8352701314492037,
    "intervention_efficacy": 0.9,
    "intervention_age_min": 0.0,
    "intervention_age_max": 5.0,
    "intervention_booster_age_max": 0.0,
    "intervention_booster_interval_years": 1.0,
    "fertility_rate": 109.25,
    "data_derived": {
      "demographics": {
        "population_used": null,
        "mean_annual_live_births_estimated": 4954514.678571428,
        "birth_rate_source": "default (set --population to calibrate birth_rate from estimated_lb)"
      },
      "intervention_coverage_from_mean_dtp1_proxy": true
    }
  },
  "calibration_scale_up_parameters": {
    "seed": 42,
    "birth_rate": 25.0,
    "death_rate": 8.0,
    "household_contacts": 5,
    "community_contacts": 15,
    "tetanus_init_p": 0.001,
    "intervention_routine_prob": 0.06687692307692307,
    "intervention_coverage": 0.8552701314492037,
    "intervention_efficacy": 0.9,
    "intervention_age_min": 0.0,
    "intervention_age_max": 5.0,
    "intervention_booster_age_max": 0.0,
    "intervention_booster_interval_years": 1.0,
    "fertility_rate": 109.25,
    "data_derived": {
      "demographics": {
        "population_used": null,
        "mean_annual_live_births_estimated": 4954514.678571428,
        "birth_rate_source": "default (set --population to calibrate birth_rate from estimated_lb)"
      },
      "intervention_coverage_from_mean_dtp1_proxy": true
    }
  },
  "projection_yearly_baseline": [
    {
      "calendar_year": 2025,
      "zerodose_under5_fraction": 0.9754701553556827,
      "n_children_under5": 2446,
      "n_zero_dose_under5": 2386,
      "tetanus_deaths": 1734
    },
    {
      "calendar_year": 2026,
      "zerodose_under5_fraction": 0.3156797331109258,
      "n_children_under5": 2398,
      "n_zero_dose_under5": 757,
      "tetanus_deaths": 1433
    },
    {
      "calendar_year": 2027,
      "zerodose_under5_fraction": 0.160352422907489,
      "n_children_under5": 2270,
      "n_zero_dose_under5": 364,
      "tetanus_deaths": 901
    },
    {
      "calendar_year": 2028,
      "zerodose_under5_fraction": 0.14192949907235622,
      "n_children_under5": 2156,
      "n_zero_dose_under5": 306,
      "tetanus_deaths": 553
    },
    {
      "calendar_year": 2029,
      "zerodose_under5_fraction": 0.13936063936063936,
      "n_children_under5": 2002,
      "n_zero_dose_under5": 279,
      "tetanus_deaths": 387
    },
    {
      "calendar_year": 2030,
      "zerodose_under5_fraction": 0.1444568868980963,
      "n_children_under5": 1786,
      "n_zero_dose_under5": 258,
      "tetanus_deaths": 4
    }
  ],
  "projection_yearly_scale_up": [
    {
      "calendar_year": 2025,
      "zerodose_under5_fraction": 0.9399018806214228,
      "n_children_under5": 2446,
      "n_zero_dose_under5": 2299,
      "tetanus_deaths": 1718
    },
    {
      "calendar_year": 2026,
      "zerodose_under5_fraction": 0.08257261410788382,
      "n_children_under5": 2410,
      "n_zero_dose_under5": 199,
      "tetanus_deaths": 1416
    },
    {
      "calendar_year": 2027,
      "zerodose_under5_fraction": 0.046704495853339155,
      "n_children_under5": 2291,
      "n_zero_dose_under5": 107,
      "tetanus_deaths": 892
    },
    {
      "calendar_year": 2028,
      "zerodose_under5_fraction": 0.06020220588235294,
      "n_children_under5": 2176,
      "n_zero_dose_under5": 131,
      "tetanus_deaths": 552
    },
    {
      "calendar_year": 2029,
      "zerodose_under5_fraction": 0.05731225296442688,
      "n_children_under5": 2024,
      "n_zero_dose_under5": 116,
      "tetanus_deaths": 385
    },
    {
      "calendar_year": 2030,
      "zerodose_under5_fraction": 0.06833333333333333,
      "n_children_under5": 1800,
      "n_zero_dose_under5": 123,
      "tetanus_deaths": 4
    }
  ],
  "projection_benefit_summary": {
    "projection_years": [
      2025,
      2026,
      2027,
      2028,
      2029,
      2030
    ],
    "mean_annual_reduction_zerodose_share_pp": 10.370375899040509,
    "cumulative_zerodose_share_reduction_pp_years": 62.22225539424306,
    "sum_annual_zero_dose_children_gap": 1375.0
  },
  "projection_tetanus_death_benefit_summary": {
    "projection_years": [
      2025,
      2026,
      2027,
      2028,
      2029,
      2030
    ],
    "total_baseline_tetanus_deaths": 5012.0,
    "total_inv_tetanus_deaths": 4967.0,
    "total_tetanus_deaths_averted": 45.0,
    "mean_annual_tetanus_deaths_averted": 7.5
  },
  "research_question_tetanus": {
    "question": "How many tetanus cases will be averted if we reduce prevalence of zero-dose vaccination by 50% among under-fives by the year 2025?",
    "modeled_answer": {
      "metric": "new_tetanus_infections_in_simulated_cohort",
      "baseline_total": 15030.0,
      "inv_total": 14934.0,
      "tetanus_cases_averted_total": 96.0,
      "by_calendar_year": [
        {
          "calendar_year": 2025,
          "baseline_tetanus_cases": 6673.0,
          "inv_tetanus_cases": 6640.0,
          "tetanus_cases_averted": 33.0
        },
        {
          "calendar_year": 2026,
          "baseline_tetanus_cases": 3694.0,
          "inv_tetanus_cases": 3669.0,
          "tetanus_cases_averted": 25.0
        },
        {
          "calendar_year": 2027,
          "baseline_tetanus_cases": 2257.0,
          "inv_tetanus_cases": 2239.0,
          "tetanus_cases_averted": 18.0
        },
        {
          "calendar_year": 2028,
          "baseline_tetanus_cases": 1432.0,
          "inv_tetanus_cases": 1420.0,
          "tetanus_cases_averted": 12.0
        },
        {
          "calendar_year": 2029,
          "baseline_tetanus_cases": 962.0,
          "inv_tetanus_cases": 954.0,
          "tetanus_cases_averted": 8.0
        },
        {
          "calendar_year": 2030,
          "baseline_tetanus_cases": 12.0,
          "inv_tetanus_cases": 12.0,
          "tetanus_cases_averted": 0.0
        }
      ],
      "modeled_zero_dose_relative_reduction_percent_end_window": 51.32473573381664
    }
  },
  "population_scaled_projection": {
    "anchor_label": "Kenya national 2024 anchors",
    "anchor_source": "UN WPP 2024; WHO/UNICEF WUENIC 2024 revision",
    "count_scale_factor": 2540.0,
    "zero_dose_children_baseline_end": 1067711,
    "zero_dose_children_inv_end": 519711,
    "zero_dose_children_reached_at_end": 548000,
    "mean_annual_children_additionally_vaccinated": 91333,
    "cumulative_child_years_zd_gap_closed": 3288000,
    "total_tetanus_deaths_averted_scaled": 114300,
    "mean_annual_tetanus_deaths_averted_scaled": 19050,
    "tetanus_cases_averted_scaled": 243840
  }
}